{
  "blogs": [
    {
      "author": "Ade",
      "content": "Lorem ipsum dolor, sit amet consectetur adipisicing elit. Omnis quasi perferendis nesciunt hic esse libero incidunt commodi accusantium assumenda, consequuntur expedita voluptas id voluptatibus saepe recusandae aut, distinctio temporibus animi? Lorem ipsum dolor, sit amet consectetur adipisicing elit. Omnis quasi perferendis nesciunt hic esse libero incidunt commodi accusantium assumenda, consequuntur expedita voluptas id voluptatibus saepe recusandae aut, distinctio temporibus animi? Lorem ipsum dolor, sit amet consectetur adipisicing elit. Omnis quasi perferendis nesciunt hic esse libero incidunt commodi accusantium assumenda, consequuntur expedita voluptas id voluptatibus saepe recusandae aut, distinctio temporibus animi? Lorem ipsum dolor, sit amet consectetur adipisicing elit. Omnis quasi perferendis nesciunt hic esse libero incidunt commodi accusantium assumenda, consequuntur expedita voluptas id voluptatibus saepe recusandae aut, distinctio temporibus animi? Lorem ipsum dolor, sit amet consectetur adipisicing elit. Omnis quasi perferendis nesciunt hic esse libero incidunt commodi accusantium assumenda, consequuntur expedita voluptas id voluptatibus saepe recusandae aut, distinctio temporibus animi? Lorem ipsum dolor, sit amet consectetur adipisicing elit. Omnis quasi perferendis nesciunt hic esse libero incidunt commodi accusantium assumenda, consequuntur expedita voluptas id voluptatibus saepe recusandae aut, distinctio temporibus animi?  ",
      "title": "About Ade",
      "id": 1
    },
    {
      "author": "Robert",
      "content": "Lorem ipsum dolor, sit amet consectetur adipisicing elit. Omnis quasi perferendis nesciunt hic esse libero incidunt commodi accusantium assumenda, consequuntur expedita voluptas id voluptatibus saepe recusandae aut, distinctio temporibus animi? Lorem ipsum dolor, sit amet consectetur adipisicing elit. Omnis quasi perferendis nesciunt hic esse libero incidunt commodi accusantium assumenda, consequuntur expedita voluptas id voluptatibus saepe recusandae aut, distinctio temporibus animi? Lorem ipsum dolor, sit amet consectetur adipisicing elit. Omnis quasi perferendis nesciunt hic esse libero incidunt commodi accusantium assumenda, consequuntur expedita voluptas id voluptatibus saepe recusandae aut, distinctio temporibus animi? Lorem ipsum dolor, sit amet consectetur adipisicing elit. Omnis quasi perferendis nesciunt hic esse libero incidunt commodi accusantium assumenda, consequuntur expedita voluptas id voluptatibus saepe recusandae aut, distinctio temporibus animi? Lorem ipsum dolor, sit amet consectetur adipisicing elit. Omnis quasi perferendis nesciunt hic esse libero incidunt commodi accusantium assumenda, consequuntur expedita voluptas id voluptatibus saepe recusandae aut, distinctio temporibus animi? Lorem ipsum dolor, sit amet consectetur adipisicing elit. Omnis quasi perferendis nesciunt hic esse libero incidunt commodi accusantium assumenda, consequuntur expedita voluptas id voluptatibus saepe recusandae aut, distinctio temporibus animi? ",
      "title": "About Robert",
      "id": 2
    },
    {
      "title": "how to avoid many problems in life",
      "content": "Live by bible principles>>>",
      "author": "ade",
      "id": 3
    },
    {
      "title": "how to be focused in life v2",
      "content": "Lorem ipsum dolor sit amet consectetur adipisicing elit. Culpa facere sit eaque hic est eum autem quae et deleniti vel voluptatem esse, quisquam facilis natus fuga quaerat aspernatur consequatur possimus sapiente accusamus. Vel labore odio voluptate repellat qui distinctio necessitatibus saepe nemo tempore velit a accusamus illo deleniti doloremque sapiente, excepturi eligendi nulla! Itaque, nihil numquam possimus excepturi, ex ipsum labore architecto, alias ipsam nobis temporibus id laborum! Doloribus delectus quasi quas nisi recusandae illo atque eligendi veritatis ab architecto minus, libero ad dolore itaque reprehenderit, dolores voluptatum harum culpa aliquam voluptas voluptate. Dolor dolorum similique molestiae ex reprehenderit excepturi quos sapiente voluptatum amet aut vel quia consectetur perferendis illo ipsam doloribus voluptates placeat dolorem unde nesciunt, dolore reiciendis quisquam dignissimos adipisci. Quaerat minus magni inventore voluptates distinctio et iste est, quasi dolor praesentium, tenetur quidem recusandae, neque reiciendis. Sapiente adipisci quos harum, tenetur, fuga facere recusandae ex dicta sunt quis voluptatem reiciendis. Maiores quaerat provident nihil. Recusandae rem ut voluptatibus sed autem nisi, fuga quis iusto accusantium natus, officiis illo delectus qui iste accusamus quas? Rerum aliquid omnis corrupti molestiae repellendus. Repellendus, dolore veritatis! Maxime, necessitatibus itaque adipisci harum repudiandae maiores cumque asperiores enim quibusdam dolor accusamus, ipsa temporibus?\n\n\nLorem ipsum dolor sit amet consectetur adipisicing elit. Culpa facere sit eaque hic est eum autem quae et deleniti vel voluptatem esse, quisquam facilis natus fuga quaerat aspernatur consequatur possimus sapiente accusamus. Vel labore odio voluptate repellat qui distinctio necessitatibus saepe nemo tempore velit a accusamus illo deleniti doloremque sapiente, excepturi eligendi nulla! Itaque, nihil numquam possimus excepturi, ex ipsum labore architecto, alias ipsam nobis temporibus id laborum! Doloribus delectus quasi quas nisi recusandae illo atque eligendi veritatis ab architecto minus, libero ad dolore itaque reprehenderit, dolores voluptatum harum culpa aliquam voluptas voluptate. Dolor dolorum similique molestiae ex reprehenderit excepturi quos sapiente voluptatum amet aut vel quia consectetur perferendis illo ipsam doloribus voluptates placeat dolorem unde nesciunt, dolore reiciendis quisquam dignissimos adipisci. Quaerat minus magni inventore voluptates distinctio et iste est, quasi dolor praesentium, tenetur quidem recusandae, neque reiciendis. Sapiente adipisci quos harum, tenetur, fuga facere recusandae ex dicta sunt quis voluptatem reiciendis. Maiores quaerat provident nihil. Recusandae rem ut voluptatibus sed autem nisi, fuga quis iusto accusantium natus, officiis illo delectus qui iste accusamus quas? Rerum aliquid omnis corrupti molestiae repellendus. Repellendus, dolore veritatis! Maxime, necessitatibus itaque adipisci harum repudiandae maiores cumque asperiores enim quibusdam dolor accusamus, ipsa temporibus?",
      "author": "Ade",
      "id": 5
    },
    {
      "title": "how to be serious in life (version 2)",
      "content": "Lorem ipsum dolor sit, amet consectetur adipisicing elit. Odit itaque quaerat incidunt explicabo quasi assumenda omnis. Culpa iure fuga amet similique, commodi maxime porro assumenda facere itaque dicta perspiciatis accusantium doloribus adipisci odit cupiditate incidunt possimus labore vero nemo harum! Atque placeat suscipit saepe! Blanditiis voluptas maiores sunt voluptatum voluptatem explicabo iusto natus exercitationem nobis aliquid et dicta ab, eum sed beatae harum cum optio ad veritatis reprehenderit magnam. Natus fugit sequi adipisci, iusto earum id cum dolorum quae laboriosam, minus assumenda ut reiciendis mollitia? Iste iusto nemo natus laborum, accusamus voluptates ullam tempora magnam debitis, sint voluptatibus ratione, eveniet nulla nihil? Sint, est alias officia veniam corporis, exercitationem id ducimus quod quaerat eaque maiores obcaecati, sequi nisi beatae. Doloribus quibusdam itaque voluptas dicta aspernatur pariatur vitae animi architecto adipisci nesciunt dolorum veniam inventore, facilis at, aliquid velit, provident sit minima? Dignissimos tempore earum corporis nemo, quibusdam assumenda iste vitae eum fugiat. Voluptate numquam, dolorum sed fugit eligendi dolor necessitatibus magnam quo amet mollitia corporis, ea obcaecati repudiandae ex suscipit perferendis? Atque omnis, ad nostrum sunt natus in error et! Tenetur fuga unde omnis illum, perspiciatis repudiandae ipsam est sit doloribus nulla hic alias aliquam, ullam assumenda quibusdam facere, voluptatibus quis qui quae. Veniam laborum qui quidem, iure voluptatem laudantium, sapiente minima ipsum ea facere nostrum ratione, in illum aperiam alias quaerat? Id maiores repudiandae a atque minus officiis expedita dignissimos modi eaque, mollitia omnis corrupti assumenda ipsum quaerat aut illum molestias quam minima asperiores autem vitae. Eligendi quam voluptas quae iure ad laboriosam nulla mollitia fugit eaque fuga aspernatur dolor, eius assumenda labore. Velit nemo earum quod autem, culpa maiores ratione veritatis totam eum neque aut quam ipsam sint vel, asperiores praesentium perferendis! Tenetur harum praesentium deleniti? Sed nam magnam nostrum veniam vero, dolor error voluptatibus recusandae maxime repudiandae, odit voluptate quod officia neque pariatur quae? Delectus alias saepe ad, natus voluptatibus quos sit consequatur facilis expedita iure? Quod, exercitationem dolorum architecto rem aliquid repudiandae iste accusamus nobis numquam placeat possimus eum recusandae et in consectetur ex illum vel molestias dolores! Qui at dolor error enim eius asperiores voluptatem quibusdam architecto dolorem! Harum dicta suscipit autem ad debitis odit enim temporibus maiores nostrum vel excepturi, pariatur iure modi beatae fugiat quam quibusdam veniam eos, numquam eaque dignissimos ducimus explicabo. Quam vero dolores repellendus perferendis debitis sed, nemo officiis vitae consequuntur expedita consequatur, commodi incidunt placeat explicabo et alias suscipit eos tempora cumque ullam excepturi facere illo impedit? Eligendi distinctio voluptas explicabo eius illo reprehenderit illum est corporis. Voluptas quidem ducimus accusantium illo a, perferendis eveniet? Quo dolores ipsum rerum assumenda alias deleniti delectus laboriosam at, nostrum molestiae, veritatis quidem aut eveniet nam velit recusandae deserunt nemo provident temporibus accusamus, molestias pariatur quibusdam beatae illum? Est eius alias accusamus dolor similique ab nisi quibusdam vel omnis unde distinctio atque nemo sapiente rem, minus eaque totam cumque maxime vitae! Est fuga itaque facere aperiam nisi, deserunt eaque accusantium. Beatae perspiciatis voluptas numquam atque modi, dignissimos dolor alias earum expedita, commodi, consequatur quos architecto? Assumenda tempora porro deserunt fuga veritatis impedit deleniti alias suscipit! Nostrum sint id est expedita libero suscipit ab quisquam ex ullam. Nisi similique minus eum blanditiis rerum sequi, unde ipsum voluptatum deleniti praesentium ratione ipsa quia id placeat ad a, culpa aspernatur facere! Similique, eligendi! Repellendus consequatur doloremque nesciunt error voluptatem ut quos excepturi, unde sapiente, possimus molestiae incidunt accusamus totam modi in itaque reiciendis asperiores quis debitis quas aliquam accusantium porro. Alias mollitia quod, reprehenderit ratione laboriosam consectetur dolorem laborum consequuntur nobis? Quidem nostrum reiciendis cupiditate ducimus delectus fugiat tenetur minima deserunt dolore alias blanditiis hic est inventore, quod tempora sapiente sit sunt ab perspiciatis minus impedit. Voluptatum asperiores, maxime aut quis iusto iure ipsa blanditiis eum quam deserunt! Impedit totam fuga ratione saepe, odio eligendi iusto quibusdam, cumque exercitationem dolorum nihil perspiciatis. Impedit animi nisi sunt minima nobis id, exercitationem optio dolorem? Magni quam, obcaecati pariatur perspiciatis similique molestias quia quae sit earum aut blanditiis repudiandae officia cum est quaerat tempora sint dolorem beatae delectus, facere voluptates. Iure iste aut tempore optio. Voluptas at nihil magnam animi et eaque assumenda aliquam, distinctio perspiciatis eos reprehenderit asperiores sapiente voluptatum explicabo porro nemo aut molestias ad esse debitis dolorem quidem quae unde cumque. Distinctio reprehenderit ab dicta tenetur quaerat voluptas vero, nulla a quia, temporibus facilis iusto sed culpa voluptatem nesciunt? Asperiores sunt, facilis dolor sint blanditiis iste voluptatum deserunt hic commodi libero excepturi sit rerum ad consequatur sed veritatis reiciendis expedita itaque amet iure! Ipsa recusandae nulla cum voluptates maiores itaque velit nisi minus ex eveniet nemo libero, quaerat sequi quibusdam, quasi, excepturi consequatur maxime ducimus repudiandae sit repellat dicta blanditiis architecto? Quae fugit quos officia facilis optio dolore dolor esse alias ipsa omnis ratione ut ipsum, eum harum itaque nobis minus temporibus beatae facere molestiae, dolorem nostrum accusantium ducimus laborum. Nemo possimus eos quaerat fugit porro voluptate vero alias tempore, consequuntur, est ab sint id eius? Inventore nobis illo odit sequi magni omnis consequatur aliquid ratione similique ducimus quod vero vitae asperiores itaque deserunt natus iure esse perferendis, enim earum explicabo adipisci deleniti commodi quae. Eveniet ullam numquam et debitis temporibus quisquam eaque. Odit, nemo fugit aliquid numquam pariatur dolore tempore ratione voluptatibus provident neque sit ipsa fugiat similique perferendis sunt officia magnam ducimus itaque sed dolor officiis, adipisci consequuntur? Nihil nisi, incidunt esse corrupti delectus dolorum repudiandae nulla necessitatibus excepturi asperiores eum aut libero eligendi ad sequi, ipsam rerum sed quod aliquid, aspernatur suscipit obcaecati fuga. Laboriosam similique quas ipsam animi eaque aspernatur quam aperiam odit dolor a iste consectetur odio eligendi tempore voluptatem, culpa optio, quo praesentium iusto. Ea, iste sint. A veritatis error voluptatibus reprehenderit atque culpa porro corporis est. Totam, veritatis maiores ab sed, vero dolorem odio tenetur tempore amet voluptatem voluptates aspernatur nam nihil nostrum aliquid quibusdam minima. Animi error est nostrum voluptate pariatur numquam eveniet sed quod soluta dignissimos? Cupiditate cumque consequuntur doloremque laudantium deleniti. Aperiam veniam, deserunt eligendi quae et repellendus officia, cupiditate dolore facere distinctio pariatur, assumenda eum.",
      "author": "praise",
      "id": 6
    },
    {
      "title": "how to remember all you read (version 2.3)",
      "content": "laidosidosdo oduisodo s\nLorem ipsum dolor sit amet consectetur adipisicing elit. Culpa facere sit eaque hic est eum autem quae et deleniti vel voluptatem esse, quisquam facilis natus fuga quaerat aspernatur consequatur possimus sapiente accusamus. Vel labore odio voluptate repellat qui distinctio necessitatibus saepe nemo tempore velit a accusamus illo deleniti doloremque sapiente, excepturi eligendi nulla! Itaque, nihil numquam possimus excepturi, ex ipsum labore architecto, alias ipsam nobis temporibus id laborum! Doloribus delectus quasi quas nisi recusandae illo atque eligendi veritatis ab architecto minus, libero ad dolore itaque reprehenderit, dolores voluptatum harum culpa aliquam voluptas voluptate. Dolor dolorum similique molestiae ex reprehenderit excepturi quos sapiente voluptatum amet aut vel quia consectetur perferendis illo ipsam doloribus voluptates placeat dolorem unde nesciunt, dolore reiciendis quisquam dignissimos adipisci. Quaerat minus magni inventore voluptates distinctio et iste est, quasi dolor praesentium, tenetur quidem recusandae, neque reiciendis. Sapiente adipisci quos harum, tenetur, fuga facere recusandae ex dicta sunt quis voluptatem reiciendis. Maiores quaerat provident nihil. Recusandae rem ut voluptatibus sed autem nisi, fuga quis iusto accusantium natus, officiis illo delectus qui iste accusamus quas? Rerum aliquid omnis corrupti molestiae repellendus. Repellendus, dolore veritatis! Maxime, necessitatibus itaque adipisci harum repudiandae maiores cumque asperiores enim quibusdam dolor accusamus, ipsa temporibus?\n\n\nLorem ipsum dolor sit amet consectetur adipisicing elit. Culpa facere sit eaque hic est eum autem quae et deleniti vel voluptatem esse, quisquam facilis natus fuga quaerat aspernatur consequatur possimus sapiente accusamus. Vel labore odio voluptate repellat qui distinctio necessitatibus saepe nemo tempore velit a accusamus illo deleniti doloremque sapiente, excepturi eligendi nulla! Itaque, nihil numquam possimus excepturi, ex ipsum labore architecto, alias ipsam nobis temporibus id laborum! Doloribus delectus quasi quas nisi recusandae illo atque eligendi veritatis ab architecto minus, libero ad dolore itaque reprehenderit, dolores voluptatum harum culpa aliquam voluptas voluptate. Dolor dolorum similique molestiae ex reprehenderit excepturi quos sapiente voluptatum amet aut vel quia consectetur perferendis illo ipsam doloribus voluptates placeat dolorem unde nesciunt, dolore reiciendis quisquam dignissimos adipisci. Quaerat minus magni inventore voluptates distinctio et iste est, quasi dolor praesentium, tenetur quidem recusandae, neque reiciendis. Sapiente adipisci quos harum, tenetur, fuga facere recusandae ex dicta sunt quis voluptatem reiciendis. Maiores quaerat provident nihil. Recusandae rem ut voluptatibus sed autem nisi, fuga quis iusto accusantium natus, officiis illo delectus qui iste accusamus quas? Rerum aliquid omnis corrupti molestiae repellendus. Repellendus, dolore veritatis! Maxime, necessitatibus itaque adipisci harum repudiandae maiores cumque asperiores enim quibusdam dolor accusamus, ipsa temporibus?",
      "author": "praise",
      "id": 7
    },
    {
      "title": "how to be punctual in a busy world V4",
      "content": "laidosidosdo oduisodo s\nLorem ipsum dolor sit amet consectetur adipisicing elit. Culpa facere sit eaque hic est eum autem quae et deleniti vel voluptatem esse, quisquam facilis natus fuga quaerat aspernatur consequatur possimus sapiente accusamus. Vel labore odio voluptate repellat qui distinctio necessitatibus saepe nemo tempore velit a accusamus illo deleniti doloremque sapiente, excepturi eligendi nulla! Itaque, nihil numquam possimus excepturi, ex ipsum labore architecto, alias ipsam nobis temporibus id laborum! Doloribus delectus quasi quas nisi recusandae illo atque eligendi veritatis ab architecto minus, libero ad dolore itaque reprehenderit, dolores voluptatum harum culpa aliquam voluptas voluptate. Dolor dolorum similique molestiae ex reprehenderit excepturi quos sapiente voluptatum amet aut vel quia consectetur perferendis illo ipsam doloribus voluptates placeat dolorem unde nesciunt, dolore reiciendis quisquam dignissimos adipisci. Quaerat minus magni inventore voluptates distinctio et iste est, quasi dolor praesentium, tenetur quidem recusandae, neque reiciendis. Sapiente adipisci quos harum, tenetur, fuga facere recusandae ex dicta sunt quis voluptatem reiciendis. Maiores quaerat provident nihil. Recusandae rem ut voluptatibus sed autem nisi, fuga quis iusto accusantium natus, officiis illo delectus qui iste accusamus quas? Rerum aliquid omnis corrupti molestiae repellendus. Repellendus, dolore veritatis! Maxime, necessitatibus itaque adipisci harum repudiandae maiores cumque asperiores enim quibusdam dolor accusamus, ipsa temporibus?\n\n\nLorem ipsum dolor sit amet consectetur adipisicing elit. Culpa facere sit eaque hic est eum autem quae et deleniti vel voluptatem esse, quisquam facilis natus fuga quaerat aspernatur consequatur possimus sapiente accusamus. Vel labore odio voluptate repellat qui distinctio necessitatibus saepe nemo tempore velit a accusamus illo deleniti doloremque sapiente, excepturi eligendi nulla! Itaque, nihil numquam possimus excepturi, ex ipsum labore architecto, alias ipsam nobis temporibus id laborum! Doloribus delectus quasi quas nisi recusandae illo atque eligendi veritatis ab architecto minus, libero ad dolore itaque reprehenderit, dolores voluptatum harum culpa aliquam voluptas voluptate. Dolor dolorum similique molestiae ex reprehenderit excepturi quos sapiente voluptatum amet aut vel quia consectetur perferendis illo ipsam doloribus voluptates placeat dolorem unde nesciunt, dolore reiciendis quisquam dignissimos adipisci. Quaerat minus magni inventore voluptates distinctio et iste est, quasi dolor praesentium, tenetur quidem recusandae, neque reiciendis. Sapiente adipisci quos harum, tenetur, fuga facere recusandae ex dicta sunt quis voluptatem reiciendis. Maiores quaerat provident nihil. Recusandae rem ut voluptatibus sed autem nisi, fuga quis iusto accusantium natus, officiis illo delectus qui iste accusamus quas? Rerum aliquid omnis corrupti molestiae repellendus. Repellendus, dolore veritatis! Maxime, necessitatibus itaque adipisci harum repudiandae maiores cumque asperiores enim quibusdam dolor accusamus, ipsa temporibus?",
      "author": "praise",
      "id": 8
    },
    {
      "title": "Mr seth's Blog",
      "content": "This is update number one",
      "author": "ade",
      "id": 9
    }
  ]
}